my_krml_25548660/__init__.py
my_krml_25548660/data/sets.py
my_krml_25548660/features/dates.py
my_krml_25548660/models/null.py
my_krml_25548660/models/performance.py
my_krml_25548660/my_krml_25548660.py
my_krml_25548660-0.1.7.dist-info/METADATA
my_krml_25548660-0.1.7.dist-info/WHEEL
my_krml_25548660-0.1.7.dist-info/RECORD
