Metadata-Version: 2.3
Name: my_krml_25548660
Version: 0.1.7
Summary: A package to preprocess data for data science projects
License: None
Author: Monika shakya
Requires-Python: >=3.11.4,<4.0.0
Classifier: License :: Other/Proprietary License
Classifier: Programming Language :: Python :: 3
Classifier: Programming Language :: Python :: 3.12
Classifier: Programming Language :: Python :: 3.13
Requires-Dist: pandas (==2.2.2)
Requires-Dist: scikit-learn (==1.5.1)
